sidetool/__init__.py
sidetool/build.py
sidetool/clean.py
sidetool/compile.py
sidetool/run.py
sidetool-0.4.8.dist-info/METADATA
sidetool-0.4.8.dist-info/WHEEL
sidetool-0.4.8.dist-info/entry_points.txt
sidetool-0.4.8.dist-info/top_level.txt
sidetool-0.4.8.dist-info/RECORD
