Metadata-Version: 2.4
Name: sidetool
Version: 0.4.8
Summary: Python Automation tool for building PySide6 UI and PyInstaller EXE.
Author-email: Alan Lilly <panofish@gmail.com>
Requires-Python: >=3.7
